dicom2fhir/__init__.py
dicom2fhir/build_terminologies.py
dicom2fhir/dicom2device.py
dicom2fhir/dicom2fhir.py
dicom2fhir/dicom2fhirbundle.py
dicom2fhir/dicom2fhirutils.py
dicom2fhir/dicom2observation.py
dicom2fhir/dicom2patient.py
dicom2fhir/dicom_json_proxy.py
dicom2fhir/helpers.py
dicom2fhir/extensions/extension_CT.py
dicom2fhir/extensions/extension_MG_CR_DX.py
dicom2fhir/extensions/extension_MR.py
dicom2fhir/extensions/extension_NM.py
dicom2fhir/extensions/extension_PT.py
dicom2fhir/extensions/extension_contrast.py
dicom2fhir/extensions/extension_instance.py
dicom2fhir/extensions/extension_reason.py
dicom2fhir/resources/terminologies/bodysite_snomed.json
dicom2fhir/resources/terminologies/radionuclide_NM.json
dicom2fhir/resources/terminologies/radionuclide_PT.json
dicom2fhir/resources/terminologies/radiopharmaceutical_NM.json
dicom2fhir/resources/terminologies/radiopharmaceutical_PT.json
dicom2fhir/resources/terminologies/units.csv
dicom2fhir/resources/terminologies/viewposition_DX.json
dicom2fhir/resources/terminologies/viewposition_DX_2.csv
dicom2fhir/resources/terminologies/viewposition_MG.json
dicom2fhir/tests/__init__.py
dicom2fhir/tests/test_dicom2fhir.py
dicom2fhir-0.1.25.dist-info/licenses/LICENSE
dicom2fhir-0.1.25.dist-info/METADATA
dicom2fhir-0.1.25.dist-info/WHEEL
dicom2fhir-0.1.25.dist-info/top_level.txt
dicom2fhir-0.1.25.dist-info/RECORD
