Metadata-Version: 2.4
Name: dicom2fhir
Version: 0.1.25
Summary: Convert dicoms to FHIR Bundles containing ImagingStudy, Patient, Device, and Observation resources.
Author-email: Felix Nensa <felix.nensa@uk-essen.de>
Project-URL: Repository, https://github.com/UMEssen/dicom-fhir-converter
Keywords: dicom,fhir,resources,python,hl7,health IT,healthcare
Classifier: Intended Audience :: Developers
Classifier: Programming Language :: Python :: 3
Classifier: Programming Language :: Python :: 3.12
Classifier: Topic :: Scientific/Engineering :: Medical Science Apps.
Classifier: Typing :: Typed
License-File: LICENSE
Requires-Dist: pydicom>=3.0.1
Requires-Dist: fhir.resources>=8.0.0
Requires-Dist: html5lib>=1.1
Requires-Dist: pandas>=2.3.0
Requires-Dist: PyYAML>=6.0.2
Requires-Dist: python-dateutil
Requires-Dist: pydantic>=2.11.5
Provides-Extra: dev
Requires-Dist: pytest>=8.4.0; extra == "dev"
Requires-Dist: psycopg2>=2.9.10; extra == "dev"
Dynamic: license-file
